Metadata-Version: 2.1
Name: dynamics-odata-client
Version: 0.1.0
Summary: Cliente OData para Dynamics 365 con autenticación y exportación a DataFrame
Home-page: https://github.com/AlbertoDuranR/dynamics_odata_client
Author: AlbertoDR
Classifier: Programming Language :: Python :: 3
Classifier: License :: OSI Approved :: MIT License
Classifier: Operating System :: OS Independent
Requires-Python: >=3.7
